[
    {
        "title": "프로그램",
        "items": [
            {
                "name": "Eclipse",
                "badge": "https://img.shields.io/badge/Eclipse-2C2255?style=for-the-badge&logo=eclipse&logoColor=white"
            },
            {
                "name": "Visual Studio Code",
                "badge": "https://custom-icon-badges.demolab.com/badge/Visual%20Studio%20Code-0078d7?style=for-the-badge&logo=vsc&logoColor=white"
            },
            {
                "name": "Dbeaver",
                "badge": "https://img.shields.io/badge/dbeaver-382923?style=for-the-badge&logo=dbeaver&logoColor=white"
            },
            {
                "name": "Spring Tool Suite (STS)",
                "badge": "https://img.shields.io/badge/Spring%20Tool%20Suite%20-6DB33F?style=for-the-badge&logo=eclipse&logoColor=white"
            },
            {
                "name": "SQL Developer",
                "badge": "https://dayoon07.github.io/static-page-test/devimg/sqldeveloper.png"
            },
            {
                "name": "Visual Studio",
                "badge": "https://custom-icon-badges.demolab.com/badge/Visual%20Studio-5C2D91.svg?&logo=visualstudio&logoColor=white&style=for-the-badge"
            },
            {
                "name": "Intellij IDEA",
                "badge": "https://img.shields.io/badge/Intellij%20Idea-000?logo=intellij-idea&style=for-the-badge"
            }
        ]
    },
    {
        "title": "언어",
        "items": [
            {
                "name": "HTML",
                "badge": "https://img.shields.io/badge/HTML5-%23E34F26?style=for-the-badge&logo=html5&logoColor=white"
            },
            {
                "name": "CSS",
                "badge": "https://img.shields.io/badge/CSS3-1572B6?style=for-the-badge&logo=css&logoColor=fff"
            },
            {
                "name": "JavaScript",
                "badge": "https://img.shields.io/badge/JavaScript-F7DF1E?style=for-the-badge&logo=javascript&logoColor=white"
            },
            {
                "name": "SQL",
                "badge": "https://img.shields.io/badge/SQL-336791?style=for-the-badge&logo=sqlite&logoColor=white"
            },
            {
                "name": "Java",
                "badge": "/img/Java-007396.svg"
            },
            {
                "name": "Markdown",
                "badge": "https://img.shields.io/badge/Markdown-%23000000.svg?logo=markdown&style=for-the-badge&logoColor=white"
            }
        ]
    },
    {
        "title": "프레임워크",
        "items": [
            {
                "name": "Spring",
                "badge": "https://img.shields.io/badge/Spring-6DB33F?style=for-the-badge&logo=spring&logoColor=white"
            },
            {
                "name": "Spring Boot",
                "badge": "https://img.shields.io/badge/Spring%20Boot-6DB33F?style=for-the-badge&logo=springboot&logoColor=fff"
            },
            {
                "name": "Spring Security",
                "badge": "https://img.shields.io/badge/Spring%20Security-6DB33F?style=for-the-badge&logo=springsecurity&logoColor=white"
            },
            {
                "name": "Spring Data JPA",
                "badge": "https://img.shields.io/badge/Spring_data_jpa-6DB33F?style=for-the-badge&logo=SpringSecurity&logoColor=white"
            },
            {
                "name": "MyBatis",
                "badge": "https://dayoon07.github.io/static-page-test/devimg/MyBatis.png"
            },
            {
                "name": "Hibernate",
                "badge": "https://img.shields.io/badge/Hibernate-59666C?style=for-the-badge&logo=hibernate&logoColor=fff"
            },
            {
                "name": "Tailwind",
                "badge": "https://img.shields.io/badge/Tailwind_CSS-38B2AC?style=for-the-badge&logo=tailwind-css&logoColor=white"
            },
            {
                "name": "Bootstrap",
                "badge": "https://img.shields.io/badge/bootstrap-%238511FA.svg?style=for-the-badge&logo=bootstrap&logoColor=white"
            }
        ]
    },
    {
        "title": "DB",
        "items": [
            {
                "name": "Oracle",
                "badge": "https://custom-icon-badges.demolab.com/badge/Oracle-F80000?style=for-the-badge&logo=oracle&logoColor=fff"
            },
            {
                "name": "Maria",
                "badge": "https://img.shields.io/badge/Maria-003545?style=for-the-badge&logo=mariadb&logoColor=white"
            }
        ]
    },
    {
        "title": "라이브러리",
        "items": [
            {
                "name": "React",
                "badge": "https://img.shields.io/badge/React-%2320232a?style=for-the-badge&logo=react&logoColor=%2361DAFB"
            },
            {
                "name": "React Router",
                "badge": "https://img.shields.io/badge/React_Router-CA4245?logo=react-router&style=for-the-badge&logoColor=white"
            },
            {
                "name": "jQuery",
                "badge": "https://img.shields.io/badge/jQuery-0769AD?style=for-the-badge&logo=jquery&logoColor=fff"
            },
            {
                "name": "Lombok",
                "badge": "https://dayoon07.github.io/static-page-test/devimg/lombok-logo.png"
            },
            {
                "name": "JSTL",
                "badge": "https://dayoon07.github.io/static-page-test/devimg/jstl.png"
            },
            {
                "name": "Chart.js",
                "badge": "https://img.shields.io/badge/Chart.js-FF6384?style=for-the-badge&logo=Chart.js&logoColor=white"
            }
        ]
    },
    {
        "title": "서버",
        "items": [
            {
                "name": "Apache Tomcat",
                "badge": "https://img.shields.io/badge/Apache%20Tomcat-F8DC75?style=for-the-badge&logo=apachetomcat&logoColor=black"
            },
            {
                "name": "Nginx",
                "badge": "https://img.shields.io/badge/Nginx-009639?logo=nginx&logoColor=white&style=for-the-badge"
            }
        ]
    },
    {
        "title": "빌드 도구",
        "items": [
            {
                "name": "Gradle",
                "badge": "https://img.shields.io/badge/Gradle-02303A?style=for-the-badge&logo=Gradle&logoColor=white"
            },
            {
                "name": "Apache Maven",
                "badge": "https://img.shields.io/badge/Maven-C71A36?style=for-the-badge&logo=apachemaven&logoColor=white"
            }
        ]
    },
    {
        "title": "분석 & 모니터링",
        "items": [
            {
                "name": "Prometheus",
                "badge": "https://img.shields.io/badge/Prometheus-black?style=for-the-badge&logo=prometheus"
            },
            {
                "name": "Grafana",
                "badge": "https://img.shields.io/badge/Grafana-F2F4F9?style=for-the-badge&logo=grafana&logoColor=orange"
            }
        ]
    }
]